llmd/__init__.py
llmd/cli.py
llmd/generator.py
llmd/parser.py
llmd/scanner.py
llmd-0.3.4.dist-info/METADATA
llmd-0.3.4.dist-info/WHEEL
llmd-0.3.4.dist-info/entry_points.txt
llmd-0.3.4.dist-info/licenses/LICENSE
llmd-0.3.4.dist-info/RECORD
