Metadata-Version: 2.4
Name: llmd
Version: 0.3.4
Summary: CLI tool for generating LLM context from GitHub repositories
License-File: LICENSE
Requires-Python: >=3.10
Requires-Dist: click>=8.2.1
Requires-Dist: pathspec>=0.12.1
